ncp/__init__.py
ncp/agent.py
ncp/agent_tool.py
ncp/cli.py
ncp/mcp_config.py
ncp/memory_config.py
ncp/model_config.py
ncp/tool.py
ncp/utils.py
ncp/commands/__init__.py
ncp/commands/authenticate.py
ncp/commands/deploy.py
ncp/commands/init.py
ncp/commands/list.py
ncp/commands/package.py
ncp/commands/playground.py
ncp/commands/remove.py
ncp/commands/validate.py
ncp/data/__init__.py
ncp/data/client.py
ncp/data/exceptions.py
ncp/templates/default/README.md
ncp/templates/default/apt-requirements.txt
ncp/templates/default/ncp.toml
ncp/templates/default/requirements.txt
ncp/templates/default/agents/__init__.py
ncp/templates/default/agents/main_agent.py
ncp/templates/default/tools/__init__.py
ncp/templates/default/tools/weather_tools.py
ncp/tools/__init__.py
ncp/tools/knowledge/__init__.py
ncp/tools/knowledge/peek.py
ncp/tools/knowledge/search.py
ncp_sdk-0.2.6.dist-info/METADATA
ncp_sdk-0.2.6.dist-info/WHEEL
ncp_sdk-0.2.6.dist-info/entry_points.txt
ncp_sdk-0.2.6.dist-info/top_level.txt
ncp_sdk-0.2.6.dist-info/RECORD
