Metadata-Version: 2.4
Name: ncp-sdk
Version: 0.2.6
Summary: SDK for building and deploying AI agents on the NCP platform
Author: Aviz Networks
License: MIT
Requires-Python: >=3.8
Requires-Dist: click>=8.0.0
Requires-Dist: pyyaml>=6.0
Requires-Dist: toml>=0.10.2
Requires-Dist: requests>=2.31.0
Requires-Dist: rich>=13.0.0
Requires-Dist: urllib3>=2.0.0
Requires-Dist: websockets>=12.0
Requires-Dist: prompt-toolkit>=3.0.0
Requires-Dist: pathspec>=0.11.0
Dynamic: requires-python
